odoo/addons/agreement_rebate_partner_company_group/README.rst
odoo/addons/agreement_rebate_partner_company_group/__init__.py
odoo/addons/agreement_rebate_partner_company_group/__manifest__.py
odoo/addons/agreement_rebate_partner_company_group/i18n/agreement_rebate_partner_company_group.pot
odoo/addons/agreement_rebate_partner_company_group/i18n/fr.po
odoo/addons/agreement_rebate_partner_company_group/i18n/it.po
odoo/addons/agreement_rebate_partner_company_group/readme/CONTRIBUTORS.md
odoo/addons/agreement_rebate_partner_company_group/readme/DESCRIPTION.md
odoo/addons/agreement_rebate_partner_company_group/readme/USAGE.md
odoo/addons/agreement_rebate_partner_company_group/static/description/icon.png
odoo/addons/agreement_rebate_partner_company_group/static/description/index.html
odoo/addons/agreement_rebate_partner_company_group/tests/__init__.py
odoo/addons/agreement_rebate_partner_company_group/tests/test_agreement_rebate.py
odoo/addons/agreement_rebate_partner_company_group/wizards/__init__.py
odoo/addons/agreement_rebate_partner_company_group/wizards/settlement_create.py
odoo_addon_agreement_rebate_partner_company_group-18.0.1.0.0.4.dist-info/METADATA
odoo_addon_agreement_rebate_partner_company_group-18.0.1.0.0.4.dist-info/WHEEL
odoo_addon_agreement_rebate_partner_company_group-18.0.1.0.0.4.dist-info/top_level.txt
odoo_addon_agreement_rebate_partner_company_group-18.0.1.0.0.4.dist-info/RECORD
