Metadata-Version: 2.1
Name: odoo-addon-agreement_rebate_partner_company_group
Version: 18.0.1.0.0.4
Requires-Python: >=3.10
Requires-Dist: odoo-addon-agreement_rebate==18.0.*
Requires-Dist: odoo-addon-base_partner_company_group==18.0.*
Requires-Dist: odoo==18.0.*
Summary: Rebate agreements applied to all company group members
Home-page: https://github.com/OCA/contract
License: AGPL-3
Author: Tecnativa, Odoo Community Association (OCA)
Author-email: support@odoo-community.org
Classifier: Programming Language :: Python
Classifier: Framework :: Odoo
Classifier: Framework :: Odoo :: 18.0
Classifier: License :: OSI Approved :: GNU Affero General Public License v3
Classifier: Development Status :: 4 - Beta
